malicense/.licsnap
malicense/LICENSE.txt
malicense/__init__.py
malicense/__main__.py
malicense/cmInterface.py
malicense/lib.py
malicense/socketcomm.py
malicense/user.py
malicense-0.0.8.dist-info/DESCRIPTION.rst
malicense-0.0.8.dist-info/METADATA
malicense-0.0.8.dist-info/RECORD
malicense-0.0.8.dist-info/WHEEL
malicense-0.0.8.dist-info/entry_points.txt
malicense-0.0.8.dist-info/metadata.json
malicense-0.0.8.dist-info/top_level.txt
