Metadata-Version: 2.0
Name: malicense
Version: 0.0.8
Summary: Verify integrity of licenses
Home-page: UNKNOWN
Author: Alex Tait
Author-email: atait@princeton.edu
License: MIT
Platform: UNKNOWN
